system_prompt_storage/__init__.py
system_prompt_storage/_base_client.py
system_prompt_storage/_client.py
system_prompt_storage/_compat.py
system_prompt_storage/_constants.py
system_prompt_storage/_exceptions.py
system_prompt_storage/_files.py
system_prompt_storage/_models.py
system_prompt_storage/_qs.py
system_prompt_storage/_resource.py
system_prompt_storage/_response.py
system_prompt_storage/_streaming.py
system_prompt_storage/_types.py
system_prompt_storage/_version.py
system_prompt_storage/py.typed
system_prompt_storage/_utils/__init__.py
system_prompt_storage/_utils/_logs.py
system_prompt_storage/_utils/_proxy.py
system_prompt_storage/_utils/_reflection.py
system_prompt_storage/_utils/_resources_proxy.py
system_prompt_storage/_utils/_streams.py
system_prompt_storage/_utils/_sync.py
system_prompt_storage/_utils/_transform.py
system_prompt_storage/_utils/_typing.py
system_prompt_storage/_utils/_utils.py
system_prompt_storage/lib/.keep
system_prompt_storage/resources/__init__.py
system_prompt_storage/resources/prompts.py
system_prompt_storage/types/__init__.py
system_prompt_storage/types/prompt.py
system_prompt_storage/types/prompt_create_params.py
system_prompt_storage/types/prompt_create_response.py
system_prompt_storage/types/prompt_list_params.py
system_prompt_storage/types/prompt_list_response.py
system_prompt_storage/types/prompt_retrieve_content_params.py
system_prompt_storage/types/prompt_retrieve_content_response.py
system_prompt_storage/types/prompt_retrieve_params.py
system_prompt_storage/types/prompt_update_metadata_params.py
system_prompt_storage/types/prompt_update_metadata_response.py
system_prompt_storage-0.1.0a5.dist-info/METADATA
system_prompt_storage-0.1.0a5.dist-info/WHEEL
system_prompt_storage-0.1.0a5.dist-info/licenses/LICENSE
system_prompt_storage-0.1.0a5.dist-info/RECORD
